{
    "tags": [],
    "description": "",
    "objects": [
        {
            "id": 1025966777,
            "classId": 10145861,
            "description": "",
            "geometryType": "rectangle",
            "labelerLogin": "akokorov",
            "createdAt": "2022-09-15T08:15:19.344Z",
            "updatedAt": "2022-09-15T08:15:19.344Z",
            "tags": [],
            "classTitle": "plant",
            "points": {
                "exterior": [
                    [
                        307.0,
                        250.0
                    ],
                    [
                        409.0,
                        386.0
                    ]
                ],
                "interior": []
            }
        }
    ],
    "size": {
        "height": 480,
        "width": 640
    }
}